aisrfwk/__init__.py
aisrfwk/aisr_queue/__init__.py
aisrfwk/aisr_queue/bussines.py
aisrfwk/aisr_queue/consume_queue.py
aisrfwk/domain/__init__.py
aisrfwk/domain/base_aisr_task.py
aisrfwk/domain/base_message.py
aisrfwk/domain/base_result.py
aisrfwk/redis/__init__.py
aisrfwk/redis/redis_core.py
aisrfwk/rocketmq/__init__.py
aisrfwk/rocketmq/rocketmq_core.py
aisrfwk/service/__init__.py
aisrfwk/service/rest_apis_demo.py
aisrfwk/util/__init__.py
aisrfwk/util/annotation_util.py
aisrfwk/util/api.py
aisrfwk/util/async_util.py
aisrfwk/util/config.py
aisrfwk/util/exception_util.py
aisrfwk/util/genid.py
aisrfwk/util/log.py
aisrfwk/util/mail_util.py
aisrfwk/util/proces_util.py
aisrfwk/util/redis_util.py
aisrfwk/util/rocketmq_util.py
aisrfwk-1.0.5.dist-info/METADATA
aisrfwk-1.0.5.dist-info/WHEEL
aisrfwk-1.0.5.dist-info/top_level.txt
aisrfwk-1.0.5.dist-info/RECORD
